<?xml version="1.0" encoding="UTF-8"?>
<comment version="3.0">
  <caption/>
  <note>Corgi Lawn Canine Pet Dog Domestic Purebred</note>
  <place/>
  <categories>
    <category value="Corgi"/>
    <category value="Dog"/>
    <category value="Lawn"/>
    <category value="Pet"/>
    <category value="Canine"/>
    <category value="Domestic"/>
    <category value="Purebred"/>
    <category value="Puppy"/>
    <category value="Mammal"/>
    <category value="Pembroke"/>
    <category value="Pedigreed"/>
    <category value="Friend"/>
    <category value="Breed"/>
    <category value="Companion"/>
    <category value="Woof"/>
    <category value="Bark"/>
    <category value="Kennel"/>
    <category value="Veterinary"/>
    <category value="Pooch"/>
    <category value="Growl"/>
    <category value="MaxPixel"/>
    <category value="FreeGreatPicture.com"/>
  </categories>
</comment>
